weather_decoder/__init__.py
weather_decoder/cli/__init__.py
weather_decoder/cli/metar_cli.py
weather_decoder/cli/taf_cli.py
weather_decoder/core/__init__.py
weather_decoder/core/metar_decoder.py
weather_decoder/core/taf_decoder.py
weather_decoder/data/__init__.py
weather_decoder/data/metar_data.py
weather_decoder/data/taf_data.py
weather_decoder/parsers/__init__.py
weather_decoder/parsers/pressure_parser.py
weather_decoder/parsers/sky_parser.py
weather_decoder/parsers/temperature_parser.py
weather_decoder/parsers/time_parser.py
weather_decoder/parsers/visibility_parser.py
weather_decoder/parsers/weather_parser.py
weather_decoder/parsers/wind_parser.py
weather_decoder/utils/__init__.py
weather_decoder/utils/constants.py
weather_decoder/utils/formatters.py
weather_decoder/utils/patterns.py
weather_decoder-1.0.7.dist-info/METADATA
weather_decoder-1.0.7.dist-info/WHEEL
weather_decoder-1.0.7.dist-info/entry_points.txt
weather_decoder-1.0.7.dist-info/top_level.txt
weather_decoder-1.0.7.dist-info/RECORD
