Metadata-Version: 2.4
Name: weather-decoder
Version: 1.0.7
Summary: A comprehensive METAR and TAF decoder for aviation weather reports
Author: Justin
Project-URL: Source, https://github.com/6639835/metar-taf-decoder
Project-URL: Bug Reports, https://github.com/6639835/metar-taf-decoder/issues
Keywords: metar taf aviation weather meteorology parsing decoder
Classifier: Development Status :: 5 - Production/Stable
Classifier: Intended Audience :: Developers
Classifier: Topic :: Scientific/Engineering :: Atmospheric Science
Classifier: License :: OSI Approved :: MIT License
Classifier: Programming Language :: Python :: 3
Classifier: Programming Language :: Python :: 3.8
Classifier: Programming Language :: Python :: 3.9
Classifier: Programming Language :: Python :: 3.10
Classifier: Programming Language :: Python :: 3.11
Classifier: Programming Language :: Python :: 3.12
Requires-Python: >=3.8
Dynamic: author
Dynamic: classifier
Dynamic: description
Dynamic: description-content-type
Dynamic: keywords
Dynamic: project-url
Dynamic: requires-python
Dynamic: summary
